{
  "main": {
    "id": "b566e3aae9e33f3a",
    "type": "split",
    "children": [
      {
        "id": "67328c18f1d0ba65",
        "type": "tabs",
        "children": [
          {
            "id": "ac171b338c3b5691",
            "type": "leaf",
            "state": {
              "type": "markdown",
              "state": {
                "file": "algebra/(25.09) Свойства определителя.md",
                "mode": "source",
                "source": false
              }
            }
          }
        ]
      }
    ],
    "direction": "vertical"
  },
  "left": {
    "id": "fa0eba65b3d97eb1",
    "type": "split",
    "children": [
      {
        "id": "44e503d5b6f4f04a",
        "type": "tabs",
        "children": [
          {
            "id": "f146d1b07d33be8a",
            "type": "leaf",
            "state": {
              "type": "file-explorer",
              "state": {
                "sortOrder": "alphabetical"
              }
            }
          },
          {
            "id": "7a9e03fc9764f827",
            "type": "leaf",
            "state": {
              "type": "search",
              "state": {
                "query": "",
                "matchingCase": false,
                "explainSearch": false,
                "collapseAll": false,
                "extraContext": false,
                "sortOrder": "alphabetical"
              }
            }
          },
          {
            "id": "8b6b46677a74888f",
            "type": "leaf",
            "state": {
              "type": "bookmarks",
              "state": {}
            }
          }
        ]
      }
    ],
    "direction": "horizontal",
    "width": 355.5
  },
  "right": {
    "id": "043a60d034339935",
    "type": "split",
    "children": [
      {
        "id": "8e3e55d250f4ecfa",
        "type": "tabs",
        "children": [
          {
            "id": "105cf4df569fb185",
            "type": "leaf",
            "state": {
              "type": "backlink",
              "state": {
                "file": "algebra/(25.09) Свойства определителя.md",
                "collapseAll": false,
                "extraContext": false,
                "sortOrder": "alphabetical",
                "showSearch": false,
                "searchQuery": "",
                "backlinkCollapsed": false,
                "unlinkedCollapsed": true
              }
            }
          },
          {
            "id": "51db94463f8baf0f",
            "type": "leaf",
            "state": {
              "type": "outgoing-link",
              "state": {
                "file": "algebra/(25.09) Свойства определителя.md",
                "linksCollapsed": false,
                "unlinkedCollapsed": true
              }
            }
          },
          {
            "id": "754761bac5ba6283",
            "type": "leaf",
            "state": {
              "type": "tag",
              "state": {
                "sortOrder": "frequency",
                "useHierarchy": true
              }
            }
          },
          {
            "id": "31e04cc43d60d1b9",
            "type": "leaf",
            "state": {
              "type": "outline",
              "state": {
                "file": "algebra/(25.09) Свойства определителя.md"
              }
            }
          },
          {
            "id": "d83867d1a32b1d6f",
            "type": "leaf",
            "state": {
              "type": "advanced-tables-toolbar",
              "state": {}
            }
          }
        ],
        "currentTab": 4
      }
    ],
    "direction": "horizontal",
    "width": 200,
    "collapsed": true
  },
  "left-ribbon": {
    "hiddenItems": {
      "switcher:Open quick switcher": false,
      "graph:Open graph view": false,
      "canvas:Create new canvas": false,
      "daily-notes:Open today's daily note": false,
      "templates:Insert template": false,
      "command-palette:Open command palette": false,
      "table-editor-obsidian:Advanced Tables Toolbar": false
    }
  },
  "active": "ac171b338c3b5691",
  "lastOpenFiles": [
    "algebra/(11.09) Преобразования и СЛУ.md",
    "algebra/(25.09) Свойства определителя.md",
    "calculus/(13.09) Индукция и последовательности.md",
    "calculus/(20.09) Сходимость и пределы.md",
    "algorithms/(17.09) Память и Типы в Языке С.md",
    "algorithms/(24.09) Переменные и операции.md",
    "algorithms/(10.09) Aлгоритмы и МТ.md",
    "algorithms/Важное.md",
    "discrete/Важное.md",
    "calculus/Важное.md",
    "algebra/Важное.md",
    "algebra/(18.09) Определители.md",
    "discrete/(20.09) Списки и индукция.md",
    "discrete/(13.09) Математическая логика 2.md",
    "discrete/Untitled",
    "calculus/(06.09) Формальная логика.md",
    "algebra/(04.09) Матрицы.md",
    "attachments/Pasted image 20240918133312.png",
    "attachments/Pasted image 20240917101658.png",
    "attachments/Pasted image 20240917101447.png",
    "attachments/Pasted image 20240912130416.png",
    "attachments/Pasted image 20240917112902.png",
    "discrete/(06.09) Математическая логика 1.md",
    "lections/attachments/Pasted image 20240917101658.png",
    "lections/attachments/Pasted image 20240912130416.png",
    "lections/attachments/Pasted image 20240917101447.png",
    "lections/attachments",
    "lections/calculus/Формальная логика (06.09).md",
    "lections/calculus/Индукция и Последовательности (13.09).md",
    "lections/calculus/Важное.md",
    "lections/calculus",
    "lections/discrete/Математическая логика 2 (13.09).md",
    "lections/discrete/Математическая логика (06.09).md",
    "lections/discrete/Важное.md",
    "lections/discrete",
    "lections/algorithms/Язык Си (17.09).md",
    "lections/algorithms/Важное.md",
    "lections/algorithms/Aлгоритмы и МТ (10.09).md",
    "lections/algorithms",
    "lections/algebra",
    "lections",
    "attachments",
    "attachements",
    "Pasted image 20240912130401.png",
    "algorithms"
  ]
}